aiverify_veritastool/__init__.py
aiverify_veritastool/__main__.py
aiverify_veritastool/algo.meta.json
aiverify_veritastool/algo.py
aiverify_veritastool/algo_init.py
aiverify_veritastool/input.schema.json
aiverify_veritastool/output.schema.json
aiverify_veritastool/plugin_init.py
aiverify_veritastool/config/config.ini
aiverify_veritastool/config/constants.py
aiverify_veritastool/metrics/__init__.py
aiverify_veritastool/metrics/fairness_metrics.py
aiverify_veritastool/metrics/modelrates.py
aiverify_veritastool/metrics/newmetric.py
aiverify_veritastool/metrics/performance_metrics.py
aiverify_veritastool/metrics/tradeoff.py
aiverify_veritastool/model/__init__.py
aiverify_veritastool/model/model_container.py
aiverify_veritastool/model/modelwrapper.py
aiverify_veritastool/principles/__init__.py
aiverify_veritastool/principles/fairness.py
aiverify_veritastool/principles/transparency.py
aiverify_veritastool/resources/specs/API_Specs_final.html
aiverify_veritastool/resources/widget/fair_class_jpg.JPG
aiverify_veritastool/resources/widget/fair_regression_jpg.JPG
aiverify_veritastool/resources/widget/fair_uplift_jpg.JPG
aiverify_veritastool/resources/widget/perf_class_jpg.JPG
aiverify_veritastool/resources/widget/perf_regression_jpg.JPG
aiverify_veritastool/resources/widget/perf_uplift_jpg.JPG
aiverify_veritastool/usecases/__init__.py
aiverify_veritastool/usecases/base_classification.py
aiverify_veritastool/usecases/base_regression.py
aiverify_veritastool/usecases/credit_scoring.py
aiverify_veritastool/usecases/customer_marketing.py
aiverify_veritastool/usecases/predictive_underwriting.py
aiverify_veritastool/util/aiverify.py
aiverify_veritastool/util/errors.py
aiverify_veritastool/util/report_plots.py
aiverify_veritastool/util/schema.py
aiverify_veritastool/util/utility.py
aiverify_veritastool/util/waterfall.py
aiverify_veritastool-2.1.0.dist-info/METADATA
aiverify_veritastool-2.1.0.dist-info/WHEEL
aiverify_veritastool-2.1.0.dist-info/entry_points.txt
aiverify_veritastool-2.1.0.dist-info/licenses/AUTHORS.rst
aiverify_veritastool-2.1.0.dist-info/licenses/LICENSE
aiverify_veritastool-2.1.0.dist-info/licenses/NOTICE.md
aiverify_veritastool-2.1.0.dist-info/RECORD
