Metadata-Version: 2.4
Name: aiverify-veritastool
Version: 2.1.0
Summary: Veritas Diagnosis tool for fairness & transparency assessment.
Author: MAS Veritas, AI Verify, Resaro
License-File: AUTHORS.rst
License-File: LICENSE
License-File: NOTICE.md
Requires-Python: <3.13,>=3.10
Requires-Dist: aiverify-test-engine>=2.1.0
Requires-Dist: ipython==8.11.0
Requires-Dist: ipywidgets==8.0.4
Requires-Dist: jinja2>=3.1.5
Requires-Dist: joblib==1.4.2
Requires-Dist: matplotlib-inline==0.1.6
Requires-Dist: matplotlib==3.10.3
Requires-Dist: numpy==1.26.4
Requires-Dist: pandas==2.2.2
Requires-Dist: phik==0.12.4
Requires-Dist: scikit-learn==1.5.2
Requires-Dist: scipy==1.14.1
Requires-Dist: seaborn==0.13.2
Requires-Dist: shap==0.46.0
Requires-Dist: tqdm>=4.67.1
